naivepool
