Metadata-Version: 1.0
Name: naivepool
Version: 0.0.4
Summary: naive thread pool of python
Home-page: https://github.com/myvyang/threadpool
Author: myvyang
Author-email: myvyang@gmail.com
License: MIT Licence
Keywords: threadpool,naivepool,thread,myvyang
Platform: any
